MANIFEST.in
setup.py
ArangoDjango.egg-info/PKG-INFO
ArangoDjango.egg-info/SOURCES.txt
ArangoDjango.egg-info/dependency_links.txt
ArangoDjango.egg-info/top_level.txt
djara/__init__.py
djara/django/__init__.py
djara/django/auth/__init__.py
djara/django/auth/admin.py
djara/django/auth/decoraters.py
djara/django/auth/fields.py
djara/django/auth/forms.py
djara/django/auth/middleware.py
djara/django/auth/models.py
djara/django/auth/models_init.py
djara/django/auth/urls.py
djara/django/auth/utils.py
djara/django/auth/views.py
djara/django/contrib/__init__.py
djara/django/contrib/models.py
djara/django/contrib/admin/__init__.py
djara/django/contrib/admin/forms.py
djara/django/contrib/admin/options.py
djara/django/contrib/admin/sites.py
djara/django/contrib/admin/urls.py
djara/django/contrib/admin/views.py
djara/django/forms/__init__.py
djara/django/forms/forms.py
djara/django/mail/__init__.py
djara/django/mail/utils.py
djara/django/menus/__init__.py
djara/django/menus/models.py
djara/django/menus/templatetags/__init__.py
djara/django/menus/templatetags/menu_tags.py
djara/django/models/__init__.py
djara/django/models/fields.py
djara/django/models/model.py
djara/django/restframework/__init__.py
djara/django/restframework/fields.py
djara/django/restframework/relations.py
djara/django/restframework/routers.py
djara/django/restframework/serializers.py
djara/django/restframework/tests.py
djara/django/restframework/viewsets.py
djara/templates/auth/user/register_email.haml
djara/templates/auth/user/register_email.html
djara/templates/djara/django/menus/simple_menu.html
djara/templates/registration/login.html