Metadata-Version: 1.1
Name: ArangoDjango
Version: 0.0.25
Summary: Bridge between the django and the arangodb world
Home-page: https://github.com/saeschdivara/ArangoDjango
Author: saskyrardisaskyr
Author-email: saeschdivara@gmail.com
License: MIT
Platform: UNKNOWN
Requires: Django
Requires: djangorestframework
Requires: ArangoPy
